{
	"loginState": 1,
	"kepler": {
		"kepler_data": null,
		"kepler_param": null
	},
	"downAppConfigData": {
		"downloadAppContentBtn": "立即打开",
		"downloadAppContentBtnStyle": "",
		"downloadAppContentDown": "实惠又轻松",
		"downloadAppContentDownStyle": "",
		"downloadAppContentUP": "打开京东APP",
		"downloadAppContentUpStyle": "",
		"downloadAppImg": "//img11.360buyimg.com/jdphoto/s640x100_jfs/t25471/63/982804166/2377/f8f633b9/5b850e48Nfd4e116b.png",
		"downloadApplogo": "//img13.360buyimg.com/img/jfs/t1/185008/26/33606/2587/641973cbFd5acd3e9/ad0294917f47e6b8.png"
	},
	"downAppUrl": "https://wqs.jd.com/downloadApp/downloadAppIOSMPage.html",
	"data": [
		{
			"compent": "AROUSAL_APP",
			"display": true,
			"isSpportUL": true,
			"msf_type": "auto",
			"openAppParam": null
		}
	],
	"cooldown": {
		"ad2": 0,
		"adod": 0,
		"auto": 1800000,
		"pcauto": 0
	},
	"shieldingLayer": {
		"newPeople_Layer": null,
		"pcScan_Layer": null
	},
	"isOpenWechat": 1,
	"coolDownTimeUtil": {
		"autoOpenApp_downCloseDate_autoOpenApp_autoPromptly": "1691067566303_1",
		"autoOpenApp_downCloseDate_jd_homePage": "1691067503680_1",
		"downloadAppPlugIn_downCloseDate": "1691066811972_1800000"
	},
	"downLoadPageSchema": "o",
	"wxDownloadSchema": "o",
	"openSendOutUrl": 0,
	"ua": {
		"appDownCloseIntervalTime": 0,
		"appDownOpenIntervalTime": 0,
		"closeUaMoreKeys": [],
		"autoCloseOs": [],
		"autoCloseBrowser": [],
		"autoCloseOsAndBrowser": []
	},
	"mediaConfigData": {
		"stepTimesLifeTime": 3600
	},
	"isNewUser": 0,
	"wechetSchemeSw": 0,
	"imkFrontGray": {
		"compressConfigGray": 1,
		"encodeGray": 1,
		"fixedBottomLayerGray": 0,
		"fixedSideLayerGray": 0,
		"iosAppId": 1,
		"iosEncodeGray": 1,
		"jingKouLingLayerGray": 0,
		"guide": 0
	},
	"bBypassSw": 1,
	"isUnpl": 1
}